setup.py
sftp.py
python_sftp_client.egg-info/PKG-INFO
python_sftp_client.egg-info/SOURCES.txt
python_sftp_client.egg-info/dependency_links.txt
python_sftp_client.egg-info/requires.txt
python_sftp_client.egg-info/top_level.txt