Metadata-Version: 1.1
Name: python_sftp_client
Version: 0.2
Summary: Python module for SFTP Client
Home-page: https://github.com/cis-yogesh/Python_sftp_client
Author: yogesh dwivedi
Author-email: yogesh.p@cisinlabs.com
License: BSD
Download-URL: https://github.com/cis-yogesh/Python_sftp_client/tarball/0.1
Keywords: python django sftp ftp
Platform: any
